mytodo/__init__.py
mytodo/model.py
mytodo/todo.py
mytodo2/__init__.py
mytodo2/model.py
mytodo2/todo.py
src/mytodo/__init__.py
src/mytodo/model.py
src/mytodo/todo.py
mytodo2-0.0.2.dist-info/METADATA
mytodo2-0.0.2.dist-info/WHEEL
mytodo2-0.0.2.dist-info/entry_points.txt
mytodo2-0.0.2.dist-info/top_level.txt
mytodo2-0.0.2.dist-info/RECORD
