Metadata-Version: 2.1
Name: mytodo2
Version: 0.0.2
Summary: Project documentation with Markdown.
Home-page: http://www.zhim.top
Author: yangzhi
Author-email: y.zhisky@163.com
License: MIT Licence
Platform: any
Classifier: Development Status :: 5 - Production/Stable
Classifier: Environment :: Console
Classifier: Environment :: Web Environment
Classifier: Intended Audience :: Developers
Classifier: License :: OSI Approved :: BSD License
Classifier: Operating System :: OS Independent
Classifier: Programming Language :: Python
Classifier: Programming Language :: Python :: 3
Classifier: Programming Language :: Python :: 3.5
Classifier: Programming Language :: Python :: 3.6
Classifier: Programming Language :: Python :: 3.7
Classifier: Programming Language :: Python :: 3.8
Classifier: Programming Language :: Python :: 3 :: Only
Classifier: Programming Language :: Python :: Implementation :: CPython
Classifier: Programming Language :: Python :: Implementation :: PyPy
Classifier: Topic :: Documentation
Classifier: Topic :: Text Processing
Requires-Python: >=3.5
Requires-Dist: setuptools (>=16.0)
Requires-Dist: Jinja2 (>=2.10.1)
Requires-Dist: beautifulsoup4 (==4.9.3)
Requires-Dist: lxml (==4.6.2)
Requires-Dist: SQLAlchemy (==1.3.22)
Requires-Dist: PyMySQL (==1.0.2)
Requires-Dist: requests (>=2.25.1)
Requires-Dist: web.py (>=0.62)
